langlearnai
