Metadata-Version: 2.1
Name: langlearnai
Version: 0.0.4
Summary: A package to produce Anki decks from list of words for language learning including automatic audio and image generation.
Author: Rogerio Gouvea
Author-email: <rogeriog.em@gmail.com>
License: UNKNOWN
Keywords: python,tts,openai,flashcards,language,learning
Platform: UNKNOWN
Classifier: Programming Language :: Python :: 3
Classifier: Operating System :: Unix
